[[{"id":203,"users_id":34,"wisata_id":31,"nama":"Hamzah Batik","latitude":"-7.7988334","longitude":"110.364721","rating":4,"kategori":"Wisata Belanja","image":"https://lh5.googleusercontent.com/p/AF1QipN0Ol5F960Hag9rp2GefQC1PBORr66I3uaN-gBv=w427-h240-k-no","url_maps":"https://goo.gl/maps/ubdxn5bwLehBeuMm8","jenis_wisata":"belanja","deskripsi":"Toko luas yang menjual kain dan pakaian batik Indonesia serta kerajinan tradisional lokal lainnya.","created_at":"2023-09-17T14:36:42.000000Z","updated_at":"2023-09-17T14:36:42.000000Z","isnight":"yes","anak":"yes","lansia":"yes","descitinerary":"Mengunjungi pusat batik yang terkenal di Jogja, Hamzah Batik","htm_weekend":"0","htm_weekday":"0"},{"id":204,"users_id":34,"wisata_id":49,"nama":"Malioboro","latitude":"-7.7982487","longitude":"110.365279","rating":5,"kategori":"Wisata Belanja","image":"https://lh5.googleusercontent.com/p/AF1QipMMLhun9fE-K4yg82IirCisQOABidfFSlJ6-Z2b=w408-h271-k-no","url_maps":"https://goo.gl/maps/9EaZ1nrkqj7WeV9q9","jenis_wisata":"belanja","deskripsi":"Malioboro adalah jantung Kota Jogja. Meskipun terkenal sebagai surga belanja cendera mata dan barang kerajinan, ternyata tak sedikit wisatawan dan orang lokal mendatangi Malioboro pagi-pagi sekali untuk berolahraga atau sekedar menikmati udara segar sambil mencari sarapan","created_at":"2023-09-17T14:36:44.000000Z","updated_at":"2023-09-17T14:36:44.000000Z","isnight":"yes","anak":"yes","lansia":"yes","descitinerary":"Menikmati suasana kota dan berbelanja di Malioboro","htm_weekend":"3000","htm_weekday":"3000"},{"id":205,"users_id":34,"wisata_id":88,"nama":"Sentra Gerabah Kasongan","latitude":"-7.8452187","longitude":"110.334123","rating":5,"kategori":"Wisata Belanja","image":"https://lh5.googleusercontent.com/p/AF1QipOYDC1M5OSIrcePtsgEeSEHJ2rkmQoS0TF-iEFI=w532-h240-k-no","url_maps":"https://goo.gl/maps/pGC3uN8wwKpRPB4eA","jenis_wisata":"belanja","deskripsi":"Kasongan mulanya merupakan tanah persawahan milik penduduk desa di selatan Yogyakarta. Pada Masa Penjajahan Belanda di Indonesia, di daerah persawahan milik salah satu warga tersebut ditemukan seekor kuda yang mati. Kuda tersebut diperkirakan milik Reserse Belanda. Karena saat itu Masa Penjajahan Belanda, maka warga yang memiliki tanah tersebut takut dan segera melepaskan hak tanahnya yang kemudian tidak diakuinya lagi. Ketakutan serupa juga terjadi pada penduduk lain yang memiliki sawah di sekitarnya yang akhirnya juga melepaskan hak tanahnya. Karena banyaknya tanah yang bebas, maka penduduk desa lain segera mengakui tanah tersebut. Penduduk yang tidak memiliki tanah tersebut kemudian beralih profesi menjadi seorang pengrajin keramik yang mulanya hanya mengempal-ngempal tanah yang tidak pecah bila disatukan. Sebenarnya tanah tersebut hanya digunakan untuk mainan anak-anak dan perabot dapur saja. Namun, karena ketekunan dan tradisi yang turun temurun, Kasongan akhirnya menjadi Desa Wisata yang cukup terkenal.","created_at":"2023-09-17T14:36:47.000000Z","updated_at":"2023-09-17T14:36:47.000000Z","isnight":"yes","anak":"yes","lansia":"yes","descitinerary":"Belanja barang dari gerabah yang unik di Kasongan","htm_weekend":"0","htm_weekday":"0"}],[{"id":206,"users_id":34,"wisata_id":109,"nama":"Pakuwon Mall","latitude":"-7.7588094","longitude":"110.396699","rating":5,"kategori":"Wisata Belanja","image":"https://lh5.googleusercontent.com/p/AF1QipORm8gLC2Hs7uVNThMJhG_xJfEsKtbimARPhj6t=w408-h284-k-no","url_maps":"https://goo.gl/maps/46NBh3prXPrZfWYk8","jenis_wisata":"belanja","deskripsi":"Mal modern dan luas dengan ratusan penyewa, termasuk department store & toko retail global.","created_at":"2023-09-17T14:36:49.000000Z","updated_at":"2023-09-17T14:36:49.000000Z","isnight":"yes","anak":"yes","lansia":"yes","descitinerary":"Belanja dan rekreasi di Pakuwon Mall","htm_weekend":"0","htm_weekday":"0"},{"id":203,"users_id":34,"wisata_id":31,"nama":"Hamzah Batik","latitude":"-7.7988334","longitude":"110.364721","rating":4,"kategori":"Wisata Belanja","image":"https://lh5.googleusercontent.com/p/AF1QipN0Ol5F960Hag9rp2GefQC1PBORr66I3uaN-gBv=w427-h240-k-no","url_maps":"https://goo.gl/maps/ubdxn5bwLehBeuMm8","jenis_wisata":"belanja","deskripsi":"Toko luas yang menjual kain dan pakaian batik Indonesia serta kerajinan tradisional lokal lainnya.","created_at":"2023-09-17T14:36:42.000000Z","updated_at":"2023-09-17T14:36:42.000000Z","isnight":"yes","anak":"yes","lansia":"yes","descitinerary":"Mengunjungi pusat batik yang terkenal di Jogja, Hamzah Batik","htm_weekend":"0","htm_weekday":"0"}]]